{"file":"public_src.png","frames":{
"item_bg_3":{"x":303,"y":539,"w":48,"h":48,"offX":0,"offY":0,"sourceW":48,"sourceH":48},
"item_bg_4":{"x":403,"y":539,"w":48,"h":48,"offX":0,"offY":0,"sourceW":48,"sourceH":48},
"item_bg_5":{"x":403,"y":489,"w":48,"h":48,"offX":0,"offY":0,"sourceW":48,"sourceH":48},
"item_qua_0":{"x":977,"y":1,"w":44,"h":44,"offX":0,"offY":0,"sourceW":44,"sourceH":44},
"item_qua_1":{"x":977,"y":231,"w":44,"h":44,"offX":0,"offY":0,"sourceW":44,"sourceH":44},
"item_qua_2":{"x":977,"y":47,"w":44,"h":44,"offX":0,"offY":0,"sourceW":44,"sourceH":44},
"item_qua_3":{"x":977,"y":93,"w":44,"h":44,"offX":0,"offY":0,"sourceW":44,"sourceH":44},
"item_qua_4":{"x":977,"y":185,"w":44,"h":44,"offX":0,"offY":0,"sourceW":44,"sourceH":44},
"item_qua_5":{"x":977,"y":139,"w":44,"h":44,"offX":0,"offY":0,"sourceW":44,"sourceH":44},
"public_1":{"x":1,"y":1,"w":460,"h":486,"offX":0,"offY":0,"sourceW":460,"sourceH":486},
"public_2":{"x":463,"y":434,"w":302,"h":520,"offX":0,"offY":0,"sourceW":302,"sourceH":520},
"public_3":{"x":630,"y":956,"w":268,"h":119,"offX":0,"offY":0,"sourceW":268,"sourceH":119},
"public_4":{"x":977,"y":405,"w":22,"h":23,"offX":0,"offY":0,"sourceW":22,"sourceH":23},
"public_5":{"x":1001,"y":405,"w":22,"h":23,"offX":0,"offY":0,"sourceW":22,"sourceH":23},
"public_6":{"x":977,"y":371,"w":32,"h":32,"offX":0,"offY":0,"sourceW":32,"sourceH":32},
"public_7":{"x":767,"y":670,"w":164,"h":71,"offX":0,"offY":0,"sourceW":164,"sourceH":71},
"public_8":{"x":990,"y":430,"w":23,"h":17,"offX":0,"offY":0,"sourceW":23,"sourceH":17},
"public_9":{"x":283,"y":956,"w":345,"h":118,"offX":0,"offY":0,"sourceW":345,"sourceH":118},
"public_10":{"x":1,"y":922,"w":280,"h":266,"offX":0,"offY":0,"sourceW":280,"sourceH":266},
"public_11":{"x":767,"y":434,"w":221,"h":234,"offX":0,"offY":0,"sourceW":221,"sourceH":234},
"public_12":{"x":463,"y":1,"w":512,"h":431,"offX":0,"offY":0,"sourceW":512,"sourceH":431},
"public_13":{"x":1,"y":489,"w":300,"h":431,"offX":0,"offY":0,"sourceW":300,"sourceH":431},
"public_14":{"x":364,"y":589,"w":59,"h":28,"offX":0,"offY":0,"sourceW":59,"sourceH":28},
"public_15":{"x":303,"y":619,"w":59,"h":28,"offX":0,"offY":0,"sourceW":59,"sourceH":28},
"public_16":{"x":364,"y":619,"w":59,"h":28,"offX":0,"offY":0,"sourceW":59,"sourceH":28},
"public_17":{"x":303,"y":649,"w":59,"h":28,"offX":0,"offY":0,"sourceW":59,"sourceH":28},
"public_18":{"x":303,"y":589,"w":59,"h":28,"offX":0,"offY":0,"sourceW":59,"sourceH":28},
"public_19":{"x":364,"y":649,"w":59,"h":28,"offX":0,"offY":0,"sourceW":59,"sourceH":28},
"public_20":{"x":303,"y":679,"w":74,"h":18,"offX":0,"offY":0,"sourceW":74,"sourceH":18},
"public_21":{"x":933,"y":670,"w":74,"h":18,"offX":0,"offY":0,"sourceW":74,"sourceH":18},
"star_0":{"x":990,"y":469,"w":18,"h":18,"offX":0,"offY":0,"sourceW":18,"sourceH":18},
"star_1":{"x":990,"y":489,"w":18,"h":18,"offX":0,"offY":0,"sourceW":18,"sourceH":18},
"star_2":{"x":990,"y":449,"w":18,"h":18,"offX":0,"offY":0,"sourceW":18,"sourceH":18},
"star_3":{"x":990,"y":509,"w":18,"h":18,"offX":0,"offY":0,"sourceW":18,"sourceH":18},
"star_10":{"x":1011,"y":371,"w":9,"h":18,"offX":0,"offY":0,"sourceW":18,"sourceH":18},
"star_20":{"x":1010,"y":449,"w":9,"h":18,"offX":0,"offY":0,"sourceW":18,"sourceH":18},
"star_30":{"x":1010,"y":469,"w":9,"h":18,"offX":0,"offY":0,"sourceW":18,"sourceH":18},
"arrow_0":{"x":977,"y":277,"w":43,"h":45,"offX":0,"offY":0,"sourceW":43,"sourceH":45},
"arrow_1":{"x":977,"y":324,"w":43,"h":45,"offX":0,"offY":0,"sourceW":43,"sourceH":45},
"item_bg_0":{"x":303,"y":489,"w":48,"h":48,"offX":0,"offY":0,"sourceW":48,"sourceH":48},
"item_bg_1":{"x":353,"y":539,"w":48,"h":48,"offX":0,"offY":0,"sourceW":48,"sourceH":48},
"item_bg_2":{"x":353,"y":489,"w":48,"h":48,"offX":0,"offY":0,"sourceW":48,"sourceH":48}}}